example_deploy_project/__init__.py
example_deploy_project/example.py
example_deploy_project-1.1.6.dist-info/METADATA
example_deploy_project-1.1.6.dist-info/WHEEL
example_deploy_project-1.1.6.dist-info/RECORD
